eazyml_dqa/__init__.cp310-win_amd64.pyd
eazyml_dqa/__init__.cp311-win_amd64.pyd
eazyml_dqa/__init__.cp312-win_amd64.pyd
eazyml_dqa/__init__.cp37-win_amd64.pyd
eazyml_dqa/__init__.cp38-win_amd64.pyd
eazyml_dqa/__init__.cp39-win_amd64.pyd
eazyml_dqa/__init__.cpython-310-x86_64-linux-gnu.so
eazyml_dqa/__init__.cpython-311-x86_64-linux-gnu.so
eazyml_dqa/__init__.cpython-38-x86_64-linux-gnu.so
eazyml_dqa/__init__.cpython-39-x86_64-linux-gnu.so
eazyml_dqa/class_balance_determiner.cp310-win_amd64.pyd
eazyml_dqa/class_balance_determiner.cp311-win_amd64.pyd
eazyml_dqa/class_balance_determiner.cp312-win_amd64.pyd
eazyml_dqa/class_balance_determiner.cp37-win_amd64.pyd
eazyml_dqa/class_balance_determiner.cp38-win_amd64.pyd
eazyml_dqa/class_balance_determiner.cp39-win_amd64.pyd
eazyml_dqa/class_balance_determiner.cpython-310-x86_64-linux-gnu.so
eazyml_dqa/class_balance_determiner.cpython-311-x86_64-linux-gnu.so
eazyml_dqa/class_balance_determiner.cpython-38-x86_64-linux-gnu.so
eazyml_dqa/class_balance_determiner.cpython-39-x86_64-linux-gnu.so
eazyml_dqa/config_data_quality.cp310-win_amd64.pyd
eazyml_dqa/config_data_quality.cp311-win_amd64.pyd
eazyml_dqa/config_data_quality.cp312-win_amd64.pyd
eazyml_dqa/config_data_quality.cp37-win_amd64.pyd
eazyml_dqa/config_data_quality.cp38-win_amd64.pyd
eazyml_dqa/config_data_quality.cp39-win_amd64.pyd
eazyml_dqa/config_data_quality.cpython-310-x86_64-linux-gnu.so
eazyml_dqa/config_data_quality.cpython-311-x86_64-linux-gnu.so
eazyml_dqa/config_data_quality.cpython-38-x86_64-linux-gnu.so
eazyml_dqa/config_data_quality.cpython-39-x86_64-linux-gnu.so
eazyml_dqa/correlation_helper.cp310-win_amd64.pyd
eazyml_dqa/correlation_helper.cp311-win_amd64.pyd
eazyml_dqa/correlation_helper.cp312-win_amd64.pyd
eazyml_dqa/correlation_helper.cp37-win_amd64.pyd
eazyml_dqa/correlation_helper.cp38-win_amd64.pyd
eazyml_dqa/correlation_helper.cp39-win_amd64.pyd
eazyml_dqa/correlation_helper.cpython-310-x86_64-linux-gnu.so
eazyml_dqa-0.0.16.dist-info/METADATA
eazyml_dqa-0.0.16.dist-info/WHEEL
eazyml_dqa-0.0.16.dist-info/top_level.txt
eazyml_dqa-0.0.16.dist-info/RECORD
