Metadata-Version: 2.1
Name: eazyml-dqa
Version: 0.0.16
Summary: Python client for data quality
Home-page: https://eazyml.com/
Author: Eazyml
Author-email: admin@ipsoftlabs.com
Project-URL: Documentation, https://eazyml.com/docs
Project-URL: Homepage, https://eazyml.com/
Keywords: python
Classifier: Development Status :: 1 - Planning
Classifier: License :: Other/Proprietary License
Classifier: Intended Audience :: Developers
Classifier: Programming Language :: Python :: 3.8
Classifier: Programming Language :: Python :: 3.9
Classifier: Programming Language :: Python :: 3.10
Classifier: Programming Language :: Python :: 3.11
Classifier: Operating System :: Unix
Classifier: Operating System :: MacOS :: MacOS X
Classifier: Operating System :: Microsoft :: Windows
Requires-Python: >=3.8
Requires-Dist: pandas==2.0.3
Requires-Dist: scikit-learn==1.3.2
Requires-Dist: numpy==1.24.3
